[
  {
    "kind": "column",
    "name": "Speed",
    "description": "Calculate pikmin's speed to carry a item.",
    "author": "nimzo6689",
    "params": [
      {
        "name": "itemName",
        "displayName": "ItemName",
        "type": "string"
      },
      {
        "name": "weight",
        "displayName": "Weight",
        "type": "number"
      },
      {
        "name": "pikminType",
        "displayName": "pikminType",
        "type": {
          "kind": "array",
          "items": "string"
        }
      },
      {
        "name": "maxCarryCount",
        "displayName": "MaxCarryCount",
        "type": "number"
      }
    ],
    "result": {
      "type": "number"
    }
  }
]
